image_dataset_loader.py
image_dataset_loader-0.0.2.dist-info/LICENSE
image_dataset_loader-0.0.2.dist-info/METADATA
image_dataset_loader-0.0.2.dist-info/WHEEL
image_dataset_loader-0.0.2.dist-info/top_level.txt
image_dataset_loader-0.0.2.dist-info/RECORD
