Metadata-Version: 2.1
Name: image-dataset-loader
Version: 0.0.2
Summary: Load image datasets as NumPy arrays
Home-page: https://github.com/soroushj/image-dataset-loader
Author: Soroush Javadi
Author-email: soroush.javadi@gmail.com
License: MIT
Keywords: datasets,image-datasets
Classifier: Development Status :: 4 - Beta
Classifier: Programming Language :: Python :: 3
Classifier: License :: OSI Approved :: MIT License
Classifier: Operating System :: OS Independent
Classifier: Topic :: Software Development :: Libraries
Classifier: Topic :: Software Development :: Libraries :: Python Modules
Classifier: Intended Audience :: Developers
Classifier: Intended Audience :: Education
Classifier: Intended Audience :: Science/Research
Requires-Python: >=3.0
License-File: LICENSE
Requires-Dist: numpy >=1.0.0
Requires-Dist: imageio >=2.0.0
